qctrltoolkit/__init__.py
qctrltoolkit/closed_loop/__init__.py
qctrltoolkit/closed_loop/functions.py
qctrltoolkit/closed_loop/nodes.py
qctrltoolkit/ions/__init__.py
qctrltoolkit/ions/functions.py
qctrltoolkit/namespace.py
qctrltoolkit/pulses/__init__.py
qctrltoolkit/pulses/functions.py
qctrltoolkit/pulses/pulse_utils.py
qctrltoolkit/pulses/pwc_nodes.py
qctrltoolkit/pulses/stf_nodes.py
qctrltoolkit/registry.py
qctrltoolkit/superconducting/__init__.py
qctrltoolkit/superconducting/functions.py
qctrltoolkit/superconducting/nodes.py
qctrltoolkit/toolkit_utils.py
qctrltoolkit/utils/functions.py
qctrltoolkit/utils/nodes.py
qctrl_toolkit-1.10.2.dist-info/LICENSE
qctrl_toolkit-1.10.2.dist-info/WHEEL
qctrl_toolkit-1.10.2.dist-info/METADATA
qctrl_toolkit-1.10.2.dist-info/RECORD
