Metadata-Version: 2.1
Name: qctrl-toolkit
Version: 1.10.2
Summary: Q-CTRL Python Toolkit
Home-page: https://q-ctrl.com
License: https://q-ctrl.com/terms
Keywords: black opal,boulder opal,nisq,open controls,q control,q ctrl,q-control,q-ctrl,qcontrol,qctrl,quantum,quantum algorithms,quantum circuits,quantum coding,quantum coding software,quantum computing,quantum control,quantum control software,quantum control theory,quantum engineering,quantum error correction,quantum firmware,quantum fundamentals,quantum sensing,qubit,qudit
Author: Q-CTRL
Author-email: support@q-ctrl.com
Maintainer: Q-CTRL
Maintainer-email: support@q-ctrl.com
Requires-Python: >=3.7.2,<3.11
Classifier: Development Status :: 5 - Production/Stable
Classifier: Environment :: Console
Classifier: Intended Audience :: Developers
Classifier: Intended Audience :: Education
Classifier: Intended Audience :: Science/Research
Classifier: License :: Other/Proprietary License
Classifier: Natural Language :: English
Classifier: Operating System :: OS Independent
Classifier: Programming Language :: Python :: 3
Classifier: Programming Language :: Python :: 3.10
Classifier: Programming Language :: Python :: 3.7
Classifier: Programming Language :: Python :: 3.8
Classifier: Programming Language :: Python :: 3.9
Classifier: Topic :: Internet :: WWW/HTTP
Classifier: Topic :: Scientific/Engineering :: Physics
Classifier: Topic :: Scientific/Engineering :: Visualization
Classifier: Topic :: Software Development :: Embedded Systems
Classifier: Topic :: System :: Distributed Computing
Requires-Dist: numpy (>=1.21.5,<2.0.0)
Requires-Dist: numpydoc (>=1.1.0,<2.0.0)
Requires-Dist: python-forge (>=18.6.0,<19.0.0)
Requires-Dist: qctrl-commons (>=17.4.1,<18.0.0)
Requires-Dist: scipy (>=1.7.3,<2.0.0)
Requires-Dist: toml (>=0.10.0,<0.11.0)
Project-URL: Facebook, https://www.facebook.com/qctrl
Project-URL: GitHub, https://github.com/qctrl
Project-URL: LinkedIn, https://www.linkedin.com/company/q-ctrl/
Project-URL: Twitter, https://twitter.com/qctrlHQ
Project-URL: YouTube, https://www.youtube.com/c/qctrl
